greptimeai/__init__.py
greptimeai/collector.py
greptimeai/openai_patcher.py
greptimeai/callbacks/langchain_callback.py
greptimeai/extractor/__init__.py
greptimeai/extractor/openai_extractor/__init__.py
greptimeai/labels/__init__.py
greptimeai/langchain/callback.py
greptimeai/patchee/__init__.py
greptimeai/patchee/openai_patchee/__init__.py
greptimeai/patchee/openai_patchee/audio.py
greptimeai/patchee/openai_patchee/chat_completion.py
greptimeai/patchee/openai_patchee/completion.py
greptimeai/patchee/openai_patchee/embedding.py
greptimeai/patchee/openai_patchee/file.py
greptimeai/patchee/openai_patchee/fine_tuning.py
greptimeai/patchee/openai_patchee/image.py
greptimeai/patchee/openai_patchee/model.py
greptimeai/patchee/openai_patchee/moderation.py
greptimeai/patchee/openai_patchee/retry.py
greptimeai/patcher/__init__.py
greptimeai/patcher/openai_patcher/base.py
greptimeai/patcher/openai_patcher/retry.py
greptimeai/patcher/openai_patcher/stream.py
greptimeai/utils/_socket.py
greptimeai/utils/attr.py
greptimeai/utils/json_encoder.py
greptimeai/utils/openai/token.py
greptimeai-0.2.1.dist-info/LICENSE
greptimeai-0.2.1.dist-info/METADATA
greptimeai-0.2.1.dist-info/WHEEL
greptimeai-0.2.1.dist-info/top_level.txt
greptimeai-0.2.1.dist-info/RECORD
