Metadata-Version: 2.1
Name: greptimeai
Version: 0.2.1
Summary: Observability tool for LLM application
Author-email: Greptime <info@greptime.com>
Keywords: greptime,greptimeai,greptimedb,observability,monitoring,llm,ai,langchain,openai
Requires-Python: >=3.8
License-File: LICENSE
Requires-Dist: opentelemetry-api >=1.20.0
Requires-Dist: opentelemetry-sdk >=1.20.0
Requires-Dist: opentelemetry-exporter-otlp-proto-http >=1.20.0
Requires-Dist: tiktoken >=0.5.1
